dj_currencies3
