Metadata-Version: 2.1
Name: dj-currencies3
Version: 1.0.2
Summary: A reusable django app that provides locally updated exchange rates to your app
Home-page: https://github.com/mthipparthi/dj-currencies
Author: Mahesh
Author-email: mahesh.thipparthi@gmail.com
License: MIT
Keywords: dj-currencies3
Platform: UNKNOWN
Classifier: Development Status :: 3 - Alpha
Classifier: Framework :: Django :: 3.0
Classifier: Intended Audience :: Developers
Classifier: License :: OSI Approved :: BSD License
Classifier: Natural Language :: English
Classifier: Programming Language :: Python :: 2
Classifier: Programming Language :: Python :: 2.7
Classifier: Programming Language :: Python :: 3
Classifier: Programming Language :: Python :: 3.4
Classifier: Programming Language :: Python :: 3.5
Classifier: Programming Language :: Python :: 3.6
